pyredditchatbot/__init__.py
pyredditchatbot/bot.py
pyredditchatbot/exceptions.py
pyredditchatbot/utils.py
tests/__init__.py
tests/integration/__init__.py
tests/unit/__init__.py
tests/unit/test_bot.py
tests/unit/test_utils.py
pyredditchatbot-0.1.3.dist-info/LICENSE
pyredditchatbot-0.1.3.dist-info/METADATA
pyredditchatbot-0.1.3.dist-info/WHEEL
pyredditchatbot-0.1.3.dist-info/top_level.txt
pyredditchatbot-0.1.3.dist-info/RECORD
