Metadata-Version: 2.1
Name: pyredditchatbot
Version: 0.1.3
Summary: A Package to build custom reddit chatbots easily
Home-page: https://github.com/Naveen-Pratap/pyredditchatbot
Author: Naveen Pratap
Author-email: naveennair1998@gmail.com
License: UNKNOWN
Project-URL: Bug Tracker, https://github.com/Naveen-Pratap/pyredditchatbot/issues
Platform: UNKNOWN
Classifier: Programming Language :: Python :: 3
Classifier: License :: OSI Approved :: BSD License
Classifier: Operating System :: OS Independent
Requires-Python: >3.6
License-File: LICENSE
Requires-Dist: praw
